testpypirpaciorek/__init__.py
testpypirpaciorek/m_mod_rp.py
testpypirpaciorek-0.0.1.dist-info/LICENSE.txt
testpypirpaciorek-0.0.1.dist-info/METADATA
testpypirpaciorek-0.0.1.dist-info/WHEEL
testpypirpaciorek-0.0.1.dist-info/top_level.txt
testpypirpaciorek-0.0.1.dist-info/RECORD
