Metadata-Version: 2.1
Name: testpypirpaciorek
Version: 0.0.1
Summary: My test package
Author-email: RP <rafal.praca.mondelez@gmail.com>
License: MIT License
Keywords: name,surname,fun function,testpypirpaciorek
Classifier: Operating System :: POSIX :: Other
Classifier: Programming Language :: Python :: 3.12
Requires-Python: >=3.0
License-File: LICENSE.txt
Requires-Dist: numpy
